README.rst
setup.cfg
setup.py
aliyunoss.egg-info/PKG-INFO
aliyunoss.egg-info/SOURCES.txt
aliyunoss.egg-info/dependency_links.txt
aliyunoss.egg-info/top_level.txt
oss/__init__.py
oss/oss_api.py
oss/oss_sample.py
oss/oss_util.py
oss/oss_xml_handler.py
oss/pkg_info.py