Metadata-Version: 1.0
Name: aliyunoss
Version: 0.3.8b2
Summary: Unofficial packaging for official aliyun oss python sdk
Home-page: http://oss.aliyun.com
Author: Aliyun OSS
Author-email: support@aliyun.com
License: MIT License
Platform: UNKNOWN
